LICENSE
kharma/__init__.py
kharma/app/__init__.py
kharma/app/_handlers.py
kharma/app/utils/arguments.py
kharma/app/utils/config.py
kharma/app/utils/exceptions.py
kharma/app/utils/numeric.py
kharma/app/utils/objects.py
kharma/app/utils/output.py
kharma/app/utils/parser.py
kharma/app/utils/regexer.py
kharma/main.py
kharma-0.0.6.dist-info/entry_points.txt
kharma-0.0.6.dist-info/LICENSE
kharma-0.0.6.dist-info/WHEEL
kharma-0.0.6.dist-info/METADATA
kharma-0.0.6.dist-info/RECORD
