Metadata-Version: 2.1
Name: kharma
Version: 0.0.6
Summary: Kharma is a state-of-the-art grammar fuzzer
Home-page: https://github.com/Rog3rSm1th/Kharma
License: MIT
Keywords: kharma,grammar,fuzzer
Author: Rog3rSm1th
Author-email: r0g3r5@protonmail.com
Requires-Python: >=3.6,<4.0
Classifier: Environment :: Console
Classifier: License :: OSI Approved :: MIT License
Classifier: Programming Language :: Python :: 3
Classifier: Programming Language :: Python :: 3.10
Classifier: Programming Language :: Python :: 3.6
Classifier: Programming Language :: Python :: 3.7
Classifier: Programming Language :: Python :: 3.8
Classifier: Programming Language :: Python :: 3.9
Requires-Dist: PyYAML (>=6.0,<7.0)
Requires-Dist: ruamel.yaml (>=0.17.21,<0.18.0)
Project-URL: Repository, https://github.com/Rog3rSm1th/Kharma
